README.md
setup.py
rdisq/__init__.py
rdisq/consumer.py
rdisq/identification.py
rdisq/payload.py
rdisq/redis_dispatcher.py
rdisq/response.py
rdisq/serialization.py
rdisq/service.py
rdisq.egg-info/PKG-INFO
rdisq.egg-info/SOURCES.txt
rdisq.egg-info/dependency_links.txt
rdisq.egg-info/requires.txt
rdisq.egg-info/top_level.txt
tests/__init__.py